{
  "project_info": {
    "project_number": "770018117414",
    "project_id": "diy-capstone-eb89d",
    "storage_bucket": "diy-capstone-eb89d.firebasestorage.app"
  },
  "client": [
    {
      "client_info": {
        "mobilesdk_app_id": "1:770018117414:android:c92921ad70c03c182de3e7",
        "android_client_info": {
          "package_name": "com.dicoding.capstone_diy"
        }
      },
      "oauth_client": [],
      "api_key": [
        {
          "current_key": "AIzaSyASYWzUmWawNX8c06FyU-vyOHYXevjYlQs"
        }
      ],
      "services": {
        "appinvite_service": {
          "other_platform_oauth_client": []
        }
      }
    }
  ],
  "configuration_version": "1"
}